<annotation>
	<folder>imgs</folder>
	<filename>861.jpg</filename>
	<path>E:\Programming\AI\DataSets\DrinkingWasteDataset\Images_of_Waste\imgs\861.jpg</path>
	<source>
		<database>Unknown</database>
	</source>
	<size>
		<width>512</width>
		<height>683</height>
		<depth>3</depth>
	</size>
	<segmented>0</segmented>
	<object>
		<name>ALU_CAN</name>
		<pose>Unspecified</pose>
		<truncated>0</truncated>
		<difficult>0</difficult>
		<bndbox>
			<xmin>130</xmin>
			<ymin>344</ymin>
			<xmax>254</xmax>
			<ymax>442</ymax>
		</bndbox>
	</object>
</annotation>
